echion/config.h
echion/_version.py
echion/greenlets.h
echion/core.pyi
echion/frame.h
echion/timing.h
echion/tasks.h
echion/cache.h
echion/core.cpython-312-darwin.so
echion/signals.h
echion/__init__.py
echion/threads.h
echion/mirrors.h
echion/long.h
echion/frame.cc
echion/coremodule.cc
echion/strings.h
echion/memory.h
echion/stack_chunk.h
echion/module.py
echion/mojo.h
echion/vm.h
echion/interp.h
echion/state.h
echion/stacks.h
echion/__main__.py
echion/render.cc
echion/render.h
echion/bootstrap/preload.py
echion/bootstrap/attach.py
echion/bootstrap/__init__.py
echion/bootstrap/sitecustomize.py
echion/cpython/tasks.h
echion/monkey/gevent.py
echion/monkey/asyncio.py
echion/monkey/__init__.py
echion/monkey/threading.py
echion-0.3.5.dist-info/RECORD
echion-0.3.5.dist-info/WHEEL
echion-0.3.5.dist-info/entry_points.txt
echion-0.3.5.dist-info/top_level.txt
echion-0.3.5.dist-info/METADATA
echion-0.3.5.dist-info/licenses/LICENSE
