Metadata-Version: 2.4
Name: echion
Version: 0.3.5
Summary: In-process CPython frame stack sampler
Author: Gabriele N. Tornetta
Author-email: "Gabriele N. Tornetta" <phoenix1987@gmail.com>
Project-URL: homepage, https://github.com/P403n1x87/echion
Project-URL: repository, https://github.com/P403n1x87/echion
Project-URL: issues, https://github.com/P403n1x87/echion/issues
Keywords: performance,profiling,testing,development
Classifier: Development Status :: 4 - Beta
Classifier: Intended Audience :: Developers
Classifier: License :: OSI Approved :: MIT License
Classifier: Programming Language :: Python :: 3.8
Classifier: Programming Language :: Python :: 3.9
Classifier: Programming Language :: Python :: 3.10
Classifier: Programming Language :: Python :: 3.11
Classifier: Programming Language :: Python :: 3.12
Classifier: Programming Language :: Python :: 3.13
Requires-Python: >=3.8
License-File: LICENSE
Requires-Dist: hypno~=1.0
Dynamic: author
Dynamic: license-file
